TrinomialTest/TrinomialTest.py
TrinomialTest/__init__.py
trinomialtest-1.0.4.dist-info/METADATA
trinomialtest-1.0.4.dist-info/WHEEL
trinomialtest-1.0.4.dist-info/licenses/LICENSE
trinomialtest-1.0.4.dist-info/RECORD
