Metadata-Version: 2.4
Name: TrinomialTest
Version: 1.0.4
Summary: A Python version of the Trinomial Test
Project-URL: Homepage, https://github.com/jrudar/TrinomialTest
Project-URL: Repository, https://github.com/jrudar/TrinomialTest.git
Project-URL: Bug Tracker, https://github.com/jrudar/TrinomialTest/issues
Author-email: Josip Rudar <joe.rudar@inspection.gc.ca>, Oliver Lung <oliver.lung@inspection.gc.ca>
License: MIT License
License-File: LICENSE
Keywords: statistics,trinomial test
Classifier: Development Status :: 5 - Production/Stable
Classifier: Intended Audience :: Science/Research
Classifier: License :: OSI Approved :: MIT License
Classifier: Natural Language :: English
Classifier: Operating System :: OS Independent
Classifier: Programming Language :: Python :: 3
Classifier: Programming Language :: Python :: 3 :: Only
Classifier: Programming Language :: Python :: 3.11
Classifier: Programming Language :: Python :: 3.12
Classifier: Programming Language :: Python :: 3.13
Requires-Python: >=3.11
Requires-Dist: numpy==2.1.3
Requires-Dist: pandas>=2.2.3
Requires-Dist: scipy>=1.15.2
Requires-Dist: statsmodels>=0.14.4
Provides-Extra: dev
Requires-Dist: black; extra == 'dev'
Requires-Dist: mypy; extra == 'dev'
Requires-Dist: ruff; extra == 'dev'
Requires-Dist: twine; extra == 'dev'
Provides-Extra: test
Requires-Dist: pytest; extra == 'test'
Requires-Dist: pytest-cov; extra == 'test'
